{
  "resources": [
    {
      "path": "data.csv",
      "name": "data",
      "profile": "tabular-data-resource",
      "scheme": "file",
      "format": "csv",
      "hashing": "md5",
      "encoding": "utf-8",
      "schema": {
        "fields": [
          {
            "name": "Year",
            "type": "integer"
          },
          {
            "name": "Coverage",
            "type": "string",
            "constraints": {
              "enum": [
                "State",
                ""
              ]
            }
          },
          {
            "name": "Units",
            "type": "string",
            "constraints": {
              "enum": [
                "High school youth with any tobacco product",
                "High school youth with cigarette",
                "Total adults with tobacco",
                ""
              ]
            }
          },
          {
            "name": "Value",
            "type": "number"
          }
        ]
      }
    }
  ],
  "profile": "data-package",
  "name": "3-a-1",
  "title": "High school youth with any use of tobacco products reported at state level"
}