{"data":{"Year":[2019,2019,2019,2019,2020,2020,2020,2020,2021,2021,2021,2021],"Race":[null,"White","Black","Other",null,"White","Black","Other",null,"White","Black","Other"],"Coverage":["Alabama","Alabama","Alabama","Alabama","Alabama","Alabama","Alabama","Alabama","Alabama","Alabama","Alabama","Alabama"],"Units":["Rate of births by state","Rate of births by state","Rate of births by state","Rate of births by state","Rate of births by state","Rate of births by state","Rate of births by state","Rate of births by state","Rate of births by state","Rate of births by state","Rate of births by state","Rate of births by state"],"Value":[6.8,5.9,8.7,6.4,6.7,5.8,8.3,6.9,6.4,5.4,8.5,6.8]},"edges":{"From":["Coverage"],"To":["Race"]}}